bhive/__init__.py
bhive/account.py
bhive/aes.py
bhive/amount.py
bhive/asciichart.py
bhive/asset.py
bhive/block.py
bhive/blockchain.py
bhive/blockchainobject.py
bhive/cli.py
bhive/comment.py
bhive/constants.py
bhive/conveyor.py
bhive/discussions.py
bhive/exceptions.py
bhive/hive.py
bhive/hiveconnect.py
bhive/imageuploader.py
bhive/instance.py
bhive/market.py
bhive/memo.py
bhive/message.py
bhive/nodelist.py
bhive/notify.py
bhive/price.py
bhive/profile.py
bhive/rc.py
bhive/snapshot.py
bhive/storage.py
bhive/transactionbuilder.py
bhive/utils.py
bhive/version.py
bhive/vote.py
bhive/wallet.py
bhive/witness.py
bhiveapi/__init__.py
bhiveapi/exceptions.py
bhiveapi/graphenerpc.py
bhiveapi/hivenoderpc.py
bhiveapi/node.py
bhiveapi/rpcutils.py
bhiveapi/version.py
bhiveapi/websocket.py
bhivebase/__init__.py
bhivebase/memo.py
bhivebase/objects.py
bhivebase/objecttypes.py
bhivebase/operationids.py
bhivebase/operations.py
bhivebase/signedtransactions.py
bhivebase/transactions.py
bhivebase/version.py
bhivegrapheneapi/__init__.py
bhivegraphenebase/__init__.py
bhivegraphenebase/account.py
bhivegraphenebase/base58.py
bhivegraphenebase/bip38.py
bhivegraphenebase/chains.py
bhivegraphenebase/dictionary.py
bhivegraphenebase/ecdsasig.py
bhivegraphenebase/objects.py
bhivegraphenebase/objecttypes.py
bhivegraphenebase/operationids.py
bhivegraphenebase/operations.py
bhivegraphenebase/py23.py
bhivegraphenebase/signedtransactions.py
bhivegraphenebase/types.py
bhivegraphenebase/version.py
bhive-0.23.21.dist-info/LICENSE.txt
bhive-0.23.21.dist-info/METADATA
bhive-0.23.21.dist-info/WHEEL
bhive-0.23.21.dist-info/entry_points.txt
bhive-0.23.21.dist-info/top_level.txt
bhive-0.23.21.dist-info/RECORD
