Metadata-Version: 2.1
Name: bhive
Version: 0.23.21
Summary: Unofficial Python library for HIVE
Home-page: http://www.github.com/thecrazygmn/bhive
Author: Holger Nahrstaedt
Author-email: thecrazygm@gmail.com
Maintainer: Holger Nahrstaedt
Maintainer-email: thecrazygm@gmail.com
License: UNKNOWN
Download-URL: https://github.com/thecrazygmn/bhive/tarball/0.23.21
Keywords: hive,library,api,rpc
Platform: UNKNOWN
Classifier: License :: OSI Approved :: MIT License
Classifier: Operating System :: OS Independent
Classifier: Programming Language :: Python
Classifier: Programming Language :: Python :: 2.7
Classifier: Programming Language :: Python :: 3
Classifier: Programming Language :: Python :: 3.4
Classifier: Programming Language :: Python :: 3.5
Classifier: Programming Language :: Python :: 3.6
Classifier: Programming Language :: Python :: 3.7
Classifier: Development Status :: 4 - Beta
Classifier: Intended Audience :: Developers
Classifier: Intended Audience :: Financial and Insurance Industry
Classifier: Topic :: Office/Business :: Financial
Requires-Dist: Click
Requires-Dist: Events
Requires-Dist: appdirs
Requires-Dist: ecdsa
Requires-Dist: future
Requires-Dist: prettytable
Requires-Dist: pycryptodomex
Requires-Dist: pylibscrypt
Requires-Dist: pytz
Requires-Dist: pyyaml
Requires-Dist: requests
Requires-Dist: scrypt
Requires-Dist: websocket-client
